LICENSE
README.rst
setup.py
com/sun/__init__.pyi
com/sun/_pyi/__init__.pyi
com/sun/_pyi/accessibility/__init__.pyi
com/sun/_pyi/accessibility/accessible.pyi
com/sun/_pyi/accessibility/accessible_context.pyi
com/sun/_pyi/accessibility/accessible_event_id.pyi
com/sun/_pyi/accessibility/accessible_event_object.pyi
com/sun/_pyi/accessibility/accessible_relation.pyi
com/sun/_pyi/accessibility/accessible_relation_type.pyi
com/sun/_pyi/accessibility/accessible_role.pyi
com/sun/_pyi/accessibility/accessible_scroll_type.pyi
com/sun/_pyi/accessibility/accessible_state_type.pyi
com/sun/_pyi/accessibility/accessible_table_model_change.pyi
com/sun/_pyi/accessibility/accessible_table_model_change_type.pyi
com/sun/_pyi/accessibility/accessible_text_type.pyi
com/sun/_pyi/accessibility/illegal_accessible_component_state_exception.pyi
com/sun/_pyi/accessibility/msaa_service.pyi
com/sun/_pyi/accessibility/text_segment.pyi
com/sun/_pyi/accessibility/x_accessible.pyi
com/sun/_pyi/accessibility/x_accessible_action.pyi
com/sun/_pyi/accessibility/x_accessible_component.pyi
com/sun/_pyi/accessibility/x_accessible_context.pyi
com/sun/_pyi/accessibility/x_accessible_context2.pyi
com/sun/_pyi/accessibility/x_accessible_context3.pyi
com/sun/_pyi/accessibility/x_accessible_editable_text.pyi
com/sun/_pyi/accessibility/x_accessible_event_broadcaster.pyi
com/sun/_pyi/accessibility/x_accessible_event_listener.pyi
com/sun/_pyi/accessibility/x_accessible_extended_attributes.pyi
com/sun/_pyi/accessibility/x_accessible_extended_component.pyi
com/sun/_pyi/accessibility/x_accessible_group_position.pyi
com/sun/_pyi/accessibility/x_accessible_hyperlink.pyi
com/sun/_pyi/accessibility/x_accessible_hypertext.pyi
com/sun/_pyi/accessibility/x_accessible_image.pyi
com/sun/_pyi/accessibility/x_accessible_key_binding.pyi
com/sun/_pyi/accessibility/x_accessible_multi_line_text.pyi
com/sun/_pyi/accessibility/x_accessible_relation_set.pyi
com/sun/_pyi/accessibility/x_accessible_selection.pyi
types_unopy.egg-info/PKG-INFO
types_unopy.egg-info/SOURCES.txt
types_unopy.egg-info/dependency_links.txt
types_unopy.egg-info/requires.txt
types_unopy.egg-info/top_level.txt