Metadata-Version: 2.1
Name: types-unopy
Version: 0.1.6
Summary: Type annotations for LibreOffice API
Home-page: https://github.com/Amourspirit/python-types-unopy
Author: :Barry-Thomas-Paul: Moss
Author-email: bigbytetech@gmail.com
License: Apache Software License
Keywords: libreoffice,openoffice,typings,uno,ooouno,pyuno
Platform: UNKNOWN
Classifier: License :: OSI Approved :: Apache Software License
Classifier: Environment :: Other Environment
Classifier: Intended Audience :: Developers
Classifier: Operating System :: OS Independent
Classifier: Topic :: Office/Business
Classifier: Typing :: Typed
Classifier: Programming Language :: Python :: 3.7
Classifier: Programming Language :: Python :: 3.8
Classifier: Programming Language :: Python :: 3.9
Classifier: Programming Language :: Python :: 3.10
Requires-Python: >=3.7.0
License-File: LICENSE
